LICENSE.txt
MANIFEST.in
README.rst
pyproject.toml
setup.py
weighted_levenshtein/__init__.py
weighted_levenshtein/clev.pxd
weighted_levenshtein/clev.pyx
weighted_levenshtein.egg-info/PKG-INFO
weighted_levenshtein.egg-info/SOURCES.txt
weighted_levenshtein.egg-info/dependency_links.txt
weighted_levenshtein.egg-info/top_level.txt